globalwaterbodycalculator/__init__.py
globalwaterbodycalculator/calculator.py
globalwaterbodycalculator/data_manager.py
globalwaterbodycalculator-0.1.3.dist-info/licenses/LICENSE
globalwaterbodycalculator-0.1.3.dist-info/METADATA
globalwaterbodycalculator-0.1.3.dist-info/WHEEL
globalwaterbodycalculator-0.1.3.dist-info/top_level.txt
globalwaterbodycalculator-0.1.3.dist-info/RECORD
